polars_istr-0.1.3.dist-info/METADATA
polars_istr-0.1.3.dist-info/WHEEL
polars_istr-0.1.3.dist-info/licenses/LICENSE.txt
polars_istr/__init__.py
polars_istr/url.py
polars_istr/isin.py
polars_istr/cusip.py
polars_istr/iban.py
polars_istr/type_alias.py
polars_istr/_utils.py
polars_istr/_polars_istr.abi3.so
polars_istr-0.1.3.dist-info/RECORD
