Metadata-Version: 2.3
Name: polars_istr
Version: 0.1.3
Classifier: Development Status :: 4 - Beta
Classifier: Programming Language :: Rust
Classifier: Programming Language :: Python :: Implementation :: CPython
Classifier: Programming Language :: Python :: Implementation :: PyPy
Classifier: License :: OSI Approved :: MIT License
Requires-Dist: polars >=1.4
Requires-Dist: typing-extensions ; python_version <= '3.11'
Requires-Dist: pytest >=7.4.1 ; extra == 'dev'
Requires-Dist: pre-commit ; extra == 'dev'
Provides-Extra: dev
License-File: LICENSE.txt
Keywords: polars-extension,string-processing,data-processing,parsing
Author-email: Tianren Qin <tq9695@gmail.com>, Connor Duncan <connor@connorduncan.xyz>
Requires-Python: >=3.8
